Workbook

Sheet 1. Assumptions
A1: SSC / GBS — Business Case Model
A2: Plantilla 5 años · Celdas amarillas = editables · Cálculo automático
A4: Parámetros generales
A5: Moneda del modelo | B5: USD
A6: Tasa de descuento / WACC | B6: 0.1
A7: Salario promedio FTE origen (fully-loaded, USD/año) | B7: 55000
A8: Costo promedio FTE Costa Rica (fully-loaded, USD/año) | B8: 26000
A9: Factor de cargas sociales CR (sobre salario base) | B9: 0.265
A10: Inflación salarial CR anual | B10: 0.05
A11: FTEs retenidos en origen (retained org) | B11: 6
A12: Management fee intercompany (% del costo SSC) | B12: 0.06
A14: Ramp-up: % del ahorro steady-state realizado por año
A15: Factor de realización del ahorro | B15: Year 0 | C15: Year 1 | D15: Year 2 | E15: Year 3 | F15: Year 4 | G15: Year 5
A16: Valor (editable) | B16: 0 | C16: 0.4 | D16: 0.8 | E16: 1 | F16: 1 | G16: 1
A18: Escenarios — multiplicadores
A19: Variable | B19: Conservador | C19: Base | D19: Optimista
A20: Multiplicador de ahorro (consolidación + automatización) | B20: 0.75 | C20: 1 | D20: 1.25
A21: Multiplicador de CAPEX | B21: 1.15 | C21: 1 | D21: 0.95
A23: Nota: edita solo celdas amarillas. Las demás hojas leen estos parámetros.

Sheet 2. Labor Arbitrage
A1: Labor Arbitrage Model
A2: Ahorro por consolidación de FTEs, por función (steady-state)
A4: Función | B4: FTEs origen | C4: Ratio consolidación | D4: FTEs en CR | E4: Costo origen (USD) | F4: Costo CR (USD) | G4: Ahorro anual (USD)
A5: AP / Procure-to-Pay | B5: 10 | C5: 2.3 | D5: =B5/C5 | E5: =B5*'1. Assumptions'!$B$7 | F5: =D5*'1. Assumptions'!$B$8 | G5: =E5-F5
A6: AR / Order-to-Cash | B6: 8 | C6: 2.4 | D6: =B6/C6 | E6: =B6*'1. Assumptions'!$B$7 | F6: =D6*'1. Assumptions'!$B$8 | G6: =E6-F6
A7: R2R / General Ledger | B7: 12 | C7: 2.2 | D7: =B7/C7 | E7: =B7*'1. Assumptions'!$B$7 | F7: =D7*'1. Assumptions'!$B$8 | G7: =E7-F7
A8: Payroll / Nómina | B8: 6 | C8: 2 | D8: =B8/C8 | E8: =B8*'1. Assumptions'!$B$7 | F8: =D8*'1. Assumptions'!$B$8 | G8: =E8-F8
A9: T&E | B9: 4 | C9: 2 | D9: =B9/C9 | E9: =B9*'1. Assumptions'!$B$7 | F9: =D9*'1. Assumptions'!$B$8 | G9: =E9-F9
A10: TOTAL | B10: =SUM(B5:B9) | D10: =SUM(D5:D9) | E10: =SUM(E5:E9) | F10: =SUM(F5:F9) | G10: =SUM(G5:G9)
A12: Retained org (costo que permanece en origen): | E12: ='1. Assumptions'!$B$11*'1. Assumptions'!$B$7

Sheet 3. Automation
A1: Automation Benefits
A2: Ahorro adicional por RPA + AI, por proceso y por año
A4: Proceso | B4: Base FTE-cost CR (USD) | C4: Autom. % objetivo | D4: Year 1 | E4: Year 2 | F4: Year 3 | G4: Year 4 | H4: Year 5
A5: AP — Invoice Processing | B5: 120000 | C5: 0.85 | D5: =$B5*$C5*'1. Assumptions'!$C$16 | E5: =$B5*$C5*'1. Assumptions'!$D$16 | F5: =$B5*$C5*'1. Assumptions'!$E$16 | G5: =$B5*$C5*'1. Assumptions'!$F$16 | H5: =$B5*$C5*'1. Assumptions'!$G$16
A6: AP — Payment Run | B6: 60000 | C6: 0.95 | D6: =$B6*$C6*'1. Assumptions'!$C$16 | E6: =$B6*$C6*'1. Assumptions'!$D$16 | F6: =$B6*$C6*'1. Assumptions'!$E$16 | G6: =$B6*$C6*'1. Assumptions'!$F$16 | H6: =$B6*$C6*'1. Assumptions'!$G$16
A7: AR — Cash Application | B7: 90000 | C7: 0.9 | D7: =$B7*$C7*'1. Assumptions'!$C$16 | E7: =$B7*$C7*'1. Assumptions'!$D$16 | F7: =$B7*$C7*'1. Assumptions'!$E$16 | G7: =$B7*$C7*'1. Assumptions'!$F$16 | H7: =$B7*$C7*'1. Assumptions'!$G$16
A8: R2R — Journals estándar | B8: 80000 | C8: 0.75 | D8: =$B8*$C8*'1. Assumptions'!$C$16 | E8: =$B8*$C8*'1. Assumptions'!$D$16 | F8: =$B8*$C8*'1. Assumptions'!$E$16 | G8: =$B8*$C8*'1. Assumptions'!$F$16 | H8: =$B8*$C8*'1. Assumptions'!$G$16
A9: R2R — Reconciliaciones | B9: 70000 | C9: 0.88 | D9: =$B9*$C9*'1. Assumptions'!$C$16 | E9: =$B9*$C9*'1. Assumptions'!$D$16 | F9: =$B9*$C9*'1. Assumptions'!$E$16 | G9: =$B9*$C9*'1. Assumptions'!$F$16 | H9: =$B9*$C9*'1. Assumptions'!$G$16
A10: T&E — Procesamiento | B10: 50000 | C10: 0.8 | D10: =$B10*$C10*'1. Assumptions'!$C$16 | E10: =$B10*$C10*'1. Assumptions'!$D$16 | F10: =$B10*$C10*'1. Assumptions'!$E$16 | G10: =$B10*$C10*'1. Assumptions'!$F$16 | H10: =$B10*$C10*'1. Assumptions'!$G$16
A11: Reporting estándar | B11: 60000 | C11: 0.9 | D11: =$B11*$C11*'1. Assumptions'!$C$16 | E11: =$B11*$C11*'1. Assumptions'!$D$16 | F11: =$B11*$C11*'1. Assumptions'!$E$16 | G11: =$B11*$C11*'1. Assumptions'!$F$16 | H11: =$B11*$C11*'1. Assumptions'!$G$16
A12: TOTAL automatización | D12: =SUM(D5:D11) | E12: =SUM(E5:E11) | F12: =SUM(F5:F11) | G12: =SUM(G5:G11) | H12: =SUM(H5:H11)

Sheet 4. One-Time Costs
A1: One-Time Costs (CAPEX)
A2: Inversión de implementación — desglose y fasaje
A4: Categoría CAPEX | B4: Year 0 | C4: Year 1 | D4: Total
A5: Consultoría (Strategy + Design + Deliver) | B5: 600000 | C5: 300000 | D5: =B5+C5
A6: Tecnología (infra + licencias año 1) | B6: 350000 | C6: 150000 | D6: =B6+C6
A7: Instalaciones (setup inicial) | B7: 300000 | C7: 100000 | D7: =B7+C7
A8: Recursos Humanos (reclutamiento + training) | B8: 250000 | C8: 100000 | D8: =B8+C8
A9: Transición (paralelismo, KT, viajes) | B9: 200000 | C9: 200000 | D9: =B9+C9
A10: TOTAL CAPEX | B10: =SUM(B5:B9) | C10: =SUM(C5:C9) | D10: =SUM(D5:D9)

Sheet 5. Operating Costs
A1: Operating Costs (OPEX Run-Rate)
A2: Costo anual de operar el GBS — Year 1..5
A4: Categoría OPEX | B4: Year 1 | C4: Year 2 | D4: Year 3 | E4: Year 4 | F4: Year 5
A5: Personal CR (post-consolidación) | B5: =SUM('2. Labor Arbitrage'!$F$5:$F$9)*(1+'1. Assumptions'!$B$10)^0 | C5: =SUM('2. Labor Arbitrage'!$F$5:$F$9)*(1+'1. Assumptions'!$B$10)^1 | D5: =SUM('2. Labor Arbitrage'!$F$5:$F$9)*(1+'1. Assumptions'!$B$10)^2 | E5: =SUM('2. Labor Arbitrage'!$F$5:$F$9)*(1+'1. Assumptions'!$B$10)^3 | F5: =SUM('2. Labor Arbitrage'!$F$5:$F$9)*(1+'1. Assumptions'!$B$10)^4
A6: Instalaciones CR (renta + servicios) | B6: 180000 | C6: =B6*(1+'1. Assumptions'!$B$10) | D6: =C6*(1+'1. Assumptions'!$B$10) | E6: =D6*(1+'1. Assumptions'!$B$10) | F6: =E6*(1+'1. Assumptions'!$B$10)
A7: Tecnología (ERP + automatización + IT) | B7: 200000 | C7: =B7*(1+'1. Assumptions'!$B$10) | D7: =C7*(1+'1. Assumptions'!$B$10) | E7: =D7*(1+'1. Assumptions'!$B$10) | F7: =E7*(1+'1. Assumptions'!$B$10)
A8: Overhead (auditoría, legal, compliance) | B8: 70000 | C8: =B8*(1+'1. Assumptions'!$B$10) | D8: =C8*(1+'1. Assumptions'!$B$10) | E8: =D8*(1+'1. Assumptions'!$B$10) | F8: =E8*(1+'1. Assumptions'!$B$10)
A9: Management fee intercompany | B9: =SUM(B5:B8)*'1. Assumptions'!$B$12 | C9: =SUM(C5:C8)*'1. Assumptions'!$B$12 | D9: =SUM(D5:D8)*'1. Assumptions'!$B$12 | E9: =SUM(E5:E8)*'1. Assumptions'!$B$12 | F9: =SUM(F5:F8)*'1. Assumptions'!$B$12
A10: TOTAL OPEX | B10: =SUM(B5:B9) | C10: =SUM(C5:C9) | D10: =SUM(D5:D9) | E10: =SUM(E5:E9) | F10: =SUM(F5:F9)
A12: Nota: defaults dimensionados para el centro CR del ejemplo (hoja 2). Escala instalaciones/tecnología con el headcount real del GBS.

Sheet 6. P&L Summary
A1: P&L Summary — Cashflow del proyecto
A2: Escenario base · ver multiplicadores en Assumptions
A4: Concepto | B4: Year 0 | C4: Year 1 | D4: Year 2 | E4: Year 3 | F4: Year 4 | G4: Year 5
A5: Ahorro bruto (labor + automatización) | B5: 0 | C5: =('2. Labor Arbitrage'!$G$10*'1. Assumptions'!$C$16+'3. Automation'!$D$12)*'1. Assumptions'!$C$20 | D5: =('2. Labor Arbitrage'!$G$10*'1. Assumptions'!$D$16+'3. Automation'!$E$12)*'1. Assumptions'!$C$20 | E5: =('2. Labor Arbitrage'!$G$10*'1. Assumptions'!$E$16+'3. Automation'!$F$12)*'1. Assumptions'!$C$20 | F5: =('2. Labor Arbitrage'!$G$10*'1. Assumptions'!$F$16+'3. Automation'!$G$12)*'1. Assumptions'!$C$20 | G5: =('2. Labor Arbitrage'!$G$10*'1. Assumptions'!$G$16+'3. Automation'!$H$12)*'1. Assumptions'!$C$20
A6: (-) Costos GBS no laborales (instal.+tech+fee) | B6: 0 | C6: =-('5. Operating Costs'!$B$10-'5. Operating Costs'!$B$5) | D6: =-('5. Operating Costs'!$C$10-'5. Operating Costs'!$C$5) | E6: =-('5. Operating Costs'!$D$10-'5. Operating Costs'!$D$5) | F6: =-('5. Operating Costs'!$E$10-'5. Operating Costs'!$E$5) | G6: =-('5. Operating Costs'!$F$10-'5. Operating Costs'!$F$5)
A7: (-) CAPEX (one-time) | B7: =-'4. One-Time Costs'!$B$10*'1. Assumptions'!$C$21 | C7: =-'4. One-Time Costs'!$C$10*'1. Assumptions'!$C$21 | D7: 0 | E7: 0 | F7: 0 | G7: 0
A8: FLUJO NETO ANUAL | B8: =SUM(B5:B7) | C8: =SUM(C5:C7) | D8: =SUM(D5:D7) | E8: =SUM(E5:E7) | F8: =SUM(F5:F7) | G8: =SUM(G5:G7)
A9: FLUJO ACUMULADO | B9: =B8 | C9: =B9+C8 | D9: =C9+D8 | E9: =D9+E8 | F9: =E9+F8 | G9: =F9+G8

Sheet 7. Financial Metrics
A1: Financial Metrics
A2: NPV · IRR · Payback · ROI (escenario base)
A4: NPV (a WACC) | B4: ='6. P&L Summary'!$B$8+NPV('1. Assumptions'!$B$6,'6. P&L Summary'!$C$8:$G$8)
A5: IRR | B5: =IFERROR(IRR('6. P&L Summary'!$B$8:$G$8),"n/a")
A6: Ahorro neto acumulado 5 años | B6: ='6. P&L Summary'!$G$9
A7: Inversión total (CAPEX) | B7: ='4. One-Time Costs'!$B$10+'4. One-Time Costs'!$C$10
A8: ROI 5 años | B8: ='6. P&L Summary'!$G$9/('4. One-Time Costs'!$B$10+'4. One-Time Costs'!$C$10)
A9: Payback (años, aprox.) | B9: =IFERROR(MATCH(TRUE,INDEX('6. P&L Summary'!$B$9:$G$9>=0,0),0)-1,"> 5")
A11: Nota: Payback usa el primer año con flujo acumulado ≥ 0.

Sheet 8. Sensitivity
A1: Sensitivity Analysis
A2: Impacto de variables clave sobre el NPV (referencia direccional)
A4: Variable | B4: Cambio | C4: Dirección impacto NPV
A5: Ratio de consolidación FTE | B5: +0.5x | C5: ▲ Alto positivo
A6: Salarios CR | B6: +10% | C6: ▼ Negativo
A7: Automatización | B7: +10 pts | C7: ▲ Positivo
A8: CAPEX implementación | B8: +20% | C8: ▼ Negativo
A9: Tipo de cambio USD/CRC | B9: ±5% | C9: ↕ Bajo
A10: Velocidad de ramp-up | B10: -3 meses | C10: ▲ Positivo
A12: Para sensibilidad cuantitativa: variar el multiplicador de ahorro/CAPEX en la hoja Assumptions y observar NPV en la hoja 7.

Sheet 9. Exec Dashboard
A1: Executive Dashboard
A2: Resumen para presentación a Junta Directiva
A4: NPV | C4: IRR | E4: Payback (años) | G4: ROI 5 años
A5: ='7. Financial Metrics'!$B$4 | C5: ='7. Financial Metrics'!$B$5 | E5: ='7. Financial Metrics'!$B$9 | G5: ='7. Financial Metrics'!$B$8
A8: Flujo acumulado | B8: Year 0 | C8: Year 1 | D8: Year 2 | E8: Year 3 | F8: Year 4 | G8: Year 5
A9: USD | B9: ='6. P&L Summary'!B9 | C9: ='6. P&L Summary'!C9 | D9: ='6. P&L Summary'!D9 | E9: ='6. P&L Summary'!E9 | F9: ='6. P&L Summary'!F9 | G9: ='6. P&L Summary'!G9
A22: Flujo neto anual | B22: Year 0 | C22: Year 1 | D22: Year 2 | E22: Year 3 | F22: Year 4 | G22: Year 5
A23: USD | B23: ='6. P&L Summary'!B8 | C23: ='6. P&L Summary'!C8 | D23: ='6. P&L Summary'!D8 | E23: ='6. P&L Summary'!E8 | F23: ='6. P&L Summary'!F8 | G23: ='6. P&L Summary'!G8
