Workbook

Sheet 1. Monthly Input
A1: SSC / GBS — KPI Dashboard
A2: Ingresa las métricas del mes (celdas amarillas). Las hojas de KPIs leen de aquí.
A4: Métrica | B4: Mes actual | C4: Mes anterior | D4: Meta | E4: Best practice
A5: P2P — Facturas procesadas (#) | B5: 12000 | C5: 11800 | D5: 13000 | E5: 15000
A6: P2P — Touchless invoice rate (%) | B6: 0.62 | C6: 0.58 | D6: 0.75 | E6: 0.85
A7: P2P — Costo por factura (USD) | B7: 4.5 | C7: 4.8 | D7: 3.5 | E7: 2.5
A8: P2P — % pagos a tiempo | B8: 0.96 | C8: 0.95 | D8: 0.98 | E8: 0.99
A9: O2C — DSO (días) | B9: 52 | C9: 55 | D9: 45 | E9: 40
A10: O2C — Cash application automática (%) | B10: 0.8 | C10: 0.76 | D10: 0.9 | E10: 0.95
A11: O2C — Collections effectiveness (%) | B11: 0.88 | C11: 0.86 | D11: 0.92 | E11: 0.95
A12: R2R — Días de cierre mensual | B12: 6 | C12: 7 | D12: 5 | E12: 4
A13: R2R — Reconciliaciones a tiempo (%) | B13: 0.9 | C13: 0.88 | D13: 0.95 | E13: 0.98
A14: R2R — Journals automatizados (%) | B14: 0.55 | C14: 0.5 | D14: 0.7 | E14: 0.8
A15: Servicio — CSAT (1-5) | B15: 4.1 | C15: 4 | D15: 4.3 | E15: 4.6
A16: Servicio — NPS | B16: 35 | C16: 32 | D16: 45 | E16: 60
... A20: People — Headcount (FTE) | B20: 180 | C20: 178 | D20: 185 | E20: 200

Sheet 2. P2P KPIs
A1: P2P KPIs
A2: Procure-to-Pay / Accounts Payable
A4: KPI | B4: Actual | C4: Anterior | D4: Meta | E4: Best pract. | F4: Status
A5: P2P — Facturas procesadas (#) | B5: ='1. Monthly Input'!$B$5 | C5: ='1. Monthly Input'!$C$5 | D5: ='1. Monthly Input'!$D$5 | E5: ='1. Monthly Input'!$E$5 | F5: =IF(B5>=D5,"🟢 Logrado",IF(B5>=D5*0.9,"🟡 En riesgo","🔴 No logrado"))
A6: P2P — Touchless invoice rate (%) | B6: ='1. Monthly Input'!$B$6 | C6: ='1. Monthly Input'!$C$6 | D6: ='1. Monthly Input'!$D$6 | E6: ='1. Monthly Input'!$E$6 | F6: =IF(B6>=D6,"🟢 Logrado",IF(B6>=D6*0.9,"🟡 En riesgo","🔴 No logrado"))
A7: P2P — Costo por factura (USD) | B7: ='1. Monthly Input'!$B$7 | C7: ='1. Monthly Input'!$C$7 | D7: ='1. Monthly Input'!$D$7 | E7: ='1. Monthly Input'!$E$7 | F7: =IF(B7<=D7,"🟢 Logrado",IF(B7<=D7*1.1,"🟡 En riesgo","🔴 No logrado"))
A8: P2P — % pagos a tiempo | B8: ='1. Monthly Input'!$B$8 | C8: ='1. Monthly Input'!$C$8 | D8: ='1. Monthly Input'!$D$8 | E8: ='1. Monthly Input'!$E$8 | F8: =IF(B8>=D8,"🟢 Logrado",IF(B8>=D8*0.9,"🟡 En riesgo","🔴 No logrado"))

Sheet 3. O2C KPIs
A1: O2C KPIs
A2: Order-to-Cash / Accounts Receivable
A4: KPI | B4: Actual | C4: Anterior | D4: Meta | E4: Best pract. | F4: Status
A5: O2C — DSO (días) | B5: ='1. Monthly Input'!$B$9 | C5: ='1. Monthly Input'!$C$9 | D5: ='1. Monthly Input'!$D$9 | E5: ='1. Monthly Input'!$E$9 | F5: =IF(B5<=D5,"🟢 Logrado",IF(B5<=D5*1.1,"🟡 En riesgo","🔴 No logrado"))
A6: O2C — Cash application automática (%) | B6: ='1. Monthly Input'!$B$10 | C6: ='1. Monthly Input'!$C$10 | D6: ='1. Monthly Input'!$D$10 | E6: ='1. Monthly Input'!$E$10 | F6: =IF(B6>=D6,"🟢 Logrado",IF(B6>=D6*0.9,"🟡 En riesgo","🔴 No logrado"))
A7: O2C — Collections effectiveness (%) | B7: ='1. Monthly Input'!$B$11 | C7: ='1. Monthly Input'!$C$11 | D7: ='1. Monthly Input'!$D$11 | E7: ='1. Monthly Input'!$E$11 | F7: =IF(B7>=D7,"🟢 Logrado",IF(B7>=D7*0.9,"🟡 En riesgo","🔴 No logrado"))

Sheet 4. R2R KPIs
A1: R2R KPIs
A2: Record-to-Report / General Ledger
A4: KPI | B4: Actual | C4: Anterior | D4: Meta | E4: Best pract. | F4: Status
A5: R2R — Días de cierre mensual | B5: ='1. Monthly Input'!$B$12 | C5: ='1. Monthly Input'!$C$12 | D5: ='1. Monthly Input'!$D$12 | E5: ='1. Monthly Input'!$E$12 | F5: =IF(B5<=D5,"🟢 Logrado",IF(B5<=D5*1.1,"🟡 En riesgo","🔴 No logrado"))
A6: R2R — Reconciliaciones a tiempo (%) | B6: ='1. Monthly Input'!$B$13 | C6: ='1. Monthly Input'!$C$13 | D6: ='1. Monthly Input'!$D$13 | E6: ='1. Monthly Input'!$E$13 | F6: =IF(B6>=D6,"🟢 Logrado",IF(B6>=D6*0.9,"🟡 En riesgo","🔴 No logrado"))
A7: R2R — Journals automatizados (%) | B7: ='1. Monthly Input'!$B$14 | C7: ='1. Monthly Input'!$C$14 | D7: ='1. Monthly Input'!$D$14 | E7: ='1. Monthly Input'!$E$14 | F7: =IF(B7>=D7,"🟢 Logrado",IF(B7>=D7*0.9,"🟡 En riesgo","🔴 No logrado"))

Sheet 5. Service KPIs
A1: Service KPIs
A2: Satisfacción y cumplimiento de servicio
A4: KPI | B4: Actual | C4: Anterior | D4: Meta | E4: Best pract. | F4: Status
A5: Servicio — CSAT (1-5) | B5: ='1. Monthly Input'!$B$15 | C5: ='1. Monthly Input'!$C$15 | D5: ='1. Monthly Input'!$D$15 | E5: ='1. Monthly Input'!$E$15 | F5: =IF(B5>=D5,"🟢 Logrado",IF(B5>=D5*0.9,"🟡 En riesgo","🔴 No logrado"))
A6: Servicio — NPS | B6: ='1. Monthly Input'!$B$16 | C6: ='1. Monthly Input'!$C$16 | D6: ='1. Monthly Input'!$D$16 | E6: ='1. Monthly Input'!$E$16 | F6: =IF(B6>=D6,"🟢 Logrado",IF(B6>=D6*0.9,"🟡 En riesgo","🔴 No logrado"))
A7: Servicio — SLA compliance (%) | B7: ='1. Monthly Input'!$B$17 | C7: ='1. Monthly Input'!$C$17 | D7: ='1. Monthly Input'!$D$17 | E7: ='1. Monthly Input'!$E$17 | F7: =IF(B7>=D7,"🟢 Logrado",IF(B7>=D7*0.9,"🟡 En riesgo","🔴 No logrado"))

Sheet 6. People KPIs
A1: People KPIs
A2: Talento y organización del GBS
A4: KPI | B4: Actual | C4: Anterior | D4: Meta | E4: Best pract. | F4: Status
A5: People — Rotación anualizada (%) | B5: ='1. Monthly Input'!$B$18 | C5: ='1. Monthly Input'!$C$18 | D5: ='1. Monthly Input'!$D$18 | E5: ='1. Monthly Input'!$E$18 | F5: =IF(B5<=D5,"🟢 Logrado",IF(B5<=D5*1.1,"🟡 En riesgo","🔴 No logrado"))
A6: People — Engagement (%) | B6: ='1. Monthly Input'!$B$19 | C6: ='1. Monthly Input'!$C$19 | D6: ='1. Monthly Input'!$D$19 | E6: ='1. Monthly Input'!$E$19 | F6: =IF(B6>=D6,"🟢 Logrado",IF(B6>=D6*0.9,"🟡 En riesgo","🔴 No logrado"))
A7: People — Headcount (FTE) | B7: ='1. Monthly Input'!$B$20 | C7: ='1. Monthly Input'!$C$20 | D7: ='1. Monthly Input'!$D$20 | E7: ='1. Monthly Input'!$E$20 | F7: =IF(B7>=D7,"🟢 Logrado",IF(B7>=D7*0.9,"🟡 En riesgo","🔴 No logrado"))

Sheet 7. Exec Dashboard
A1: Executive Dashboard
A2: RAG status + tendencia para el Comité de Operaciones
A4: KPI clave | B4: Actual | C4: Meta | D4: Status
A5: Touchless invoice rate (%) | B5: ='1. Monthly Input'!$B$6 | C5: ='1. Monthly Input'!$D$6 | D5: =IF(B5>=C5,"🟢",IF(B5>=C5*0.9,"🟡","🔴"))
A6: DSO (días) | B6: ='1. Monthly Input'!$B$9 | C6: ='1. Monthly Input'!$D$9 | D6: =IF(B6<=C6,"🟢",IF(B6<=C6*1.1,"🟡","🔴"))
A7: Días de cierre | B7: ='1. Monthly Input'!$B$12 | C7: ='1. Monthly Input'!$D$12 | D7: =IF(B7<=C7,"🟢",IF(B7<=C7*1.1,"🟡","🔴"))
A8: SLA compliance (%) | B8: ='1. Monthly Input'!$B$17 | C8: ='1. Monthly Input'!$D$17 | D8: =IF(B8>=C8,"🟢",IF(B8>=C8*0.9,"🟡","🔴"))
A9: CSAT | B9: ='1. Monthly Input'!$B$15 | C9: ='1. Monthly Input'!$D$15 | D9: =IF(B9>=C9,"🟢",IF(B9>=C9*0.9,"🟡","🔴"))
A10: Rotación (%) | B10: ='1. Monthly Input'!$B$18 | C10: ='1. Monthly Input'!$D$18 | D10: =IF(B10<=C10,"🟢",IF(B10<=C10*1.1,"🟡","🔴"))
A13: Tendencia (editable) — Touchless rate % | B13: M-5 | C13: M-4 | D13: M-3 | E13: M-2 | F13: M-1 | G13: Actual
A14: Touchless % | B14: 0.52 | C14: 0.55 | D14: 0.57 | E14: 0.58 | F14: 0.6 | G14: ='1. Monthly Input'!$B$6

Sheet 8. Benchmark
A1: Benchmark Comparison
A2: Actual vs. best practice (Hackett / APQC referencial)
A4: KPI | B4: Actual | C4: Best practice | D4: Gap | E4: % del benchmark
A5: P2P — Facturas procesadas (#) | B5: ='1. Monthly Input'!$B$5 | C5: ='1. Monthly Input'!$E$5 | D5: =B5-C5 | E5: =IFERROR(B5/C5,"n/a")
A6: P2P — Touchless invoice rate (%) | B6: ='1. Monthly Input'!$B$6 | C6: ='1. Monthly Input'!$E$6 | D6: =B6-C6 | E6: =IFERROR(B6/C6,"n/a")
A7: P2P — Costo por factura (USD) | B7: ='1. Monthly Input'!$B$7 | C7: ='1. Monthly Input'!$E$7 | D7: =B7-C7 | E7: =IFERROR(B7/C7,"n/a")
A8: P2P — % pagos a tiempo | B8: ='1. Monthly Input'!$B$8 | C8: ='1. Monthly Input'!$E$8 | D8: =B8-C8 | E8: =IFERROR(B8/C8,"n/a")
A9: O2C — DSO (días) | B9: ='1. Monthly Input'!$B$9 | C9: ='1. Monthly Input'!$E$9 | D9: =B9-C9 | E9: =IFERROR(B9/C9,"n/a")
A10: O2C — Cash application automática (%) | B10: ='1. Monthly Input'!$B$10 | C10: ='1. Monthly Input'!$E$10 | D10: =B10-C10 | E10: =IFERROR(B10/C10,"n/a")
A11: O2C — Collections effectiveness (%) | B11: ='1. Monthly Input'!$B$11 | C11: ='1. Monthly Input'!$E$11 | D11: =B11-C11 | E11: =IFERROR(B11/C11,"n/a")
A12: R2R — Días de cierre mensual | B12: ='1. Monthly Input'!$B$12 | C12: ='1. Monthly Input'!$E$12 | D12: =B12-C12 | E12: =IFERROR(B12/C12,"n/a")
A13: R2R — Reconciliaciones a tiempo (%) | B13: ='1. Monthly Input'!$B$13 | C13: ='1. Monthly Input'!$E$13 | D13: =B13-C13 | E13: =IFERROR(B13/C13,"n/a")
A14: R2R — Journals automatizados (%) | B14: ='1. Monthly Input'!$B$14 | C14: ='1. Monthly Input'!$E$14 | D14: =B14-C14 | E14: =IFERROR(B14/C14,"n/a")
A15: Servicio — CSAT (1-5) | B15: ='1. Monthly Input'!$B$15 | C15: ='1. Monthly Input'!$E$15 | D15: =B15-C15 | E15: =IFERROR(B15/C15,"n/a")
A16: Servicio — NPS | B16: ='1. Monthly Input'!$B$16 | C16: ='1. Monthly Input'!$E$16 | D16: =B16-C16 | E16: =IFERROR(B16/C16,"n/a")
A17: Servicio — SLA compliance (%) | B17: ='1. Monthly Input'!$B$17 | C17: ='1. Monthly Input'!$E$17 | D17: =B17-C17 | E17: =IFERROR(B17/C17,"n/a")
A18: People — Rotación anualizada (%) | B18: ='1. Monthly Input'!$B$18 | C18: ='1. Monthly Input'!$E$18 | D18: =B18-C18 | E18: =IFERROR(B18/C18,"n/a")
A19: People — Engagement (%) | B19: ='1. Monthly Input'!$B$19 | C19: ='1. Monthly Input'!$E$19 | D19: =B19-C19 | E19: =IFERROR(B19/C19,"n/a")
A20: People — Headcount (FTE) | B20: ='1. Monthly Input'!$B$20 | C20: ='1. Monthly Input'!$E$20 | D20: =B20-C20 | E20: =IFERROR(B20/C20,"n/a")
